odoo/addons/account_budget_propagate_date/README.rst
odoo/addons/account_budget_propagate_date/__init__.py
odoo/addons/account_budget_propagate_date/__manifest__.py
odoo/addons/account_budget_propagate_date/models/__init__.py
odoo/addons/account_budget_propagate_date/models/crossovered_budget.py
odoo/addons/account_budget_propagate_date/static/description/icon.png
odoo/addons/account_budget_propagate_date/views/crossovered_budget_view.xml
odoo_addon_account_budget_propagate_date-15.0.1.0.0.dist-info/METADATA
odoo_addon_account_budget_propagate_date-15.0.1.0.0.dist-info/WHEEL
odoo_addon_account_budget_propagate_date-15.0.1.0.0.dist-info/top_level.txt
odoo_addon_account_budget_propagate_date-15.0.1.0.0.dist-info/RECORD
